README.md
setup.cfg
setup.py
telepyth/__init__.py
telepyth/cli.py
telepyth/client.py
telepyth/magics.py
telepyth/multipart.py
telepyth/utils.py
telepyth/version.py
telepyth.egg-info/PKG-INFO
telepyth.egg-info/SOURCES.txt
telepyth.egg-info/dependency_links.txt
telepyth.egg-info/entry_points.txt
telepyth.egg-info/top_level.txt