Metadata-Version: 1.1
Name: telepyth
Version: 0.1.6
Summary: TelePyth: Telegram notifications in Python.
Home-page: https://github.com/daskol/telepyth
Author: Daniel Bershatsky
Author-email: daniel.bershatsky@skolkovotech.ru
License: MIT
Download-URL: https://github.com/daskol/telepyth/tarball/v0.1.6
Platform: Windows
Platform: Linux
Platform: Solaris
Platform: Mac OS-X
Platform: Unix
Classifier: Development Status :: 4 - Beta
Classifier: Intended Audience :: Science/Research
Classifier: Intended Audience :: Developers
Classifier: License :: OSI Approved :: MIT License
Classifier: Programming Language :: Python
Classifier: Topic :: Software Development
Classifier: Topic :: Scientific/Engineering
Classifier: Operating System :: Microsoft :: Windows
Classifier: Operating System :: POSIX
Classifier: Operating System :: Unix
Classifier: Operating System :: MacOS
